hcuppy/__init__.py
hcuppy/cci.py
hcuppy/ccs.py
hcuppy/cpt.py
hcuppy/elixhauser.py
hcuppy/prcls.py
hcuppy/sflag.py
hcuppy/uflag.py
hcuppy/utils.py
hcuppy/data/ICD10PCS_utilizationflagformats_FY2019_1.csv
hcuppy/data/__init__.py
hcuppy/data/cci_icd10cm_2019_1.csv
hcuppy/data/ccs_dx_icd10cm_2019_1.csv
hcuppy/data/ccs_pr_icd10pcs_2019_1.csv
hcuppy/data/comindex2012-2015.txt
hcuppy/data/cpt_sections.csv
hcuppy/data/dxmlabel10.csv
hcuppy/data/elix_comformat_icd10cm_2019_1.txt
hcuppy/data/elix_comoanaly_icd10cm_2019_1.txt
hcuppy/data/license.txt
hcuppy/data/pc_icd10pcs_2018.csv
hcuppy/data/prmlabel10.csv
hcuppy/data/surgery_flags_cpt_2017.csv
hcuppy-0.0.7.dist-info/LICENSE.txt
hcuppy-0.0.7.dist-info/METADATA
hcuppy-0.0.7.dist-info/WHEEL
hcuppy-0.0.7.dist-info/top_level.txt
hcuppy-0.0.7.dist-info/RECORD
