Metadata-Version: 2.1
Name: hcuppy
Version: 0.0.7
Summary: hcuppy is a Python implementation of HCUP Tools and Software
Home-page: https://github.com/yubin-park/hcuppy
Author: Yubin Park
Author-email: yubin.park@gmail.com
License: Apaceh 2.0
Platform: UNKNOWN
Classifier: Programming Language :: Python :: 3
Classifier: License :: OSI Approved :: Apache Software License
Classifier: Operating System :: OS Independent
